moogle/Search.py
moogle/__init__.py
moogle/DataStructures/SearchResult.py
moogle/DataStructures/__init__.py
Moogle-1.0.1.dist-info/LICENSE.txt
Moogle-1.0.1.dist-info/METADATA
Moogle-1.0.1.dist-info/WHEEL
Moogle-1.0.1.dist-info/top_level.txt
Moogle-1.0.1.dist-info/RECORD
