Metadata-Version: 2.1
Name: Moogle
Version: 1.0.1
Summary: 📦 Google Search API - Simple Python Package
Home-page: https://github.com/diezo/moogle
Download-URL: https://github.com/diezo/moogle/archive/refs/tags/v1.0.1.tar.gz
Author: Deepak Soni
Author-email: sonniiii@outlook.com
License: MIT
Keywords: python,google,google-api,google-search,python-google,google-search-api,python-google-search
Classifier: Development Status :: 5 - Production/Stable
Classifier: Intended Audience :: Developers
Classifier: Topic :: Software Development :: Build Tools
Classifier: License :: OSI Approved :: MIT License
Classifier: Programming Language :: Python :: 3
Classifier: Programming Language :: Python :: 3.10
License-File: LICENSE.txt
Requires-Dist: requests
Requires-Dist: bs4
